pydantic_ai_graph/__init__.py
pydantic_ai_graph/_utils.py
pydantic_ai_graph/graph.py
pydantic_ai_graph/nodes.py
pydantic_ai_graph/state.py
pydantic_ai_graph-0.0.1.dist-info/METADATA
pydantic_ai_graph-0.0.1.dist-info/WHEEL
pydantic_ai_graph-0.0.1.dist-info/RECORD
